setup.py
FTClient/FTClient.py
FTClient/__init__.py
FTClient/sql/__init__.py
FTClient/sql/sqlbuilder.py
FTSync/MysqlFTSync.py
FTSync/PostgresFTSync.py
FTSync/__init__.py
FTTools.egg-info/PKG-INFO
FTTools.egg-info/SOURCES.txt
FTTools.egg-info/dependency_links.txt
FTTools.egg-info/top_level.txt
scripts/ft-sync