Metadata-Version: 1.0
Name: FTTools
Version: 1.1.6
Summary: SkyTruth Fusion Table Tools
Home-page: http://www.skytruth.org/
Author: Paul Woods
Author-email: pau@skytruth.org
License: UNKNOWN
Platform: UNKNOWN
